<?xml version="1.0" encoding="UTF-8" standalone="no" ?>
<vms>
	<vm>
		<name>VCPR-NMS-BABS-00</name>
		<description></description>
		<environment>Produktions-Umgebung</environment>
		<location>NMS - Stao A</location>
		<subnetnode>TN NMS (NMS)</subnetnode>
		<cpu>8 CPU</cpu>			
		<memory>16 GB Memory</memory>
		<disk>300 GB Disk (VMDK - Thin Provisioning),300 GB Disk (VMDK - Thin Provisioning)</disk>
		<vmh>VMH-NMS-BABS-00 [NMS - Stao A]</vmh>
		<subnet></subnet>
		<dg></dg>
		<mask></mask>				
		<ip></ip>
	</vm>
	<vm>
		<name>PRP-NMS-BABS-00</name>
		<description></description>
		<environment>Produktions-Umgebung</environment>
		<location>NMS - Stao A</location>
		<subnetnode>TN NMS (NMS)</subnetnode>
		<cpu>2 CPU</cpu>			
		<memory>8 GB Memory</memory>
		<disk>120 GB Disk (VMDK - Thin Provisioning)</disk>
		<vmh>VMH-NMS-BABS-00 [NMS - Stao A]</vmh>
		<subnet></subnet>
		<dg></dg>
		<mask></mask>				
		<ip></ip>
	</vm>
	<vm>
		<name>VCPM-NMS-BABS-00</name>
		<description></description>
		<environment>Produktions-Umgebung</environment>
		<location>NMS - Stao A</location>
		<subnetnode>TN NMS (NMS)</subnetnode>
		<cpu>8 CPU</cpu>			
		<memory>96 GB Memory</memory>
		<disk>250 GB Disk (VMDK - Thin Provisioning)</disk>
		<vmh>VMH-NMS-BABS-00 [NMS - Stao A]</vmh>
		<subnet></subnet>
		<dg></dg>
		<mask></mask>				
		<ip></ip>
	</vm>
	<vm>
		<name>VCPL-NMS-BABS-00</name>
		<description></description>
		<environment>Produktions-Umgebung</environment>
		<location>NMS - Stao A</location>
		<subnetnode>TN NMS (NMS)</subnetnode>
		<cpu>4 CPU</cpu>			
		<memory>64 GB Memory</memory>
		<disk>1000 GB Disk (VMDK - Thin Provisioning)</disk>
		<vmh>VMH-NMS-BABS-00 [NMS - Stao A]</vmh>
		<subnet></subnet>
		<dg></dg>
		<mask></mask>				
		<ip></ip>
	</vm>
	<vm>
		<name>NPS-NMS-BABS-00</name>
		<description></description>
		<environment>Produktions-Umgebung</environment>
		<location>NMS - Stao A</location>
		<subnetnode>TN NMS (NMS)</subnetnode>
		<cpu>4 CPU</cpu>			
		<memory>8 GB Memory</memory>
		<disk>120 GB Disk (VMDK - Thin Provisioning),20 GB Disk (VMDK - Thin Provisioning)</disk>
		<vmh>VMH-NMS-BABS-00 [NMS - Stao A]</vmh>
		<subnet></subnet>
		<dg></dg>
		<mask></mask>				
		<ip></ip>
	</vm>
	<vm>
		<name>JMP-NMS-BABS-01</name>
		<description></description>
		<environment>Produktions-Umgebung</environment>
		<location>NMS - Stao A</location>
		<subnetnode>TN NMS (NMS)</subnetnode>
		<cpu>4 CPU</cpu>			
		<memory>16 GB Memory</memory>
		<disk>120 GB Disk (VMDK - Thin Provisioning)</disk>
		<vmh>VMH-NMS-BABS-00 [NMS - Stao A]</vmh>
		<subnet></subnet>
		<dg></dg>
		<mask></mask>				
		<ip></ip>
	</vm>
	<vm>
		<name>MCS-NMS-BABS-00</name>
		<description></description>
		<environment>Produktions-Umgebung</environment>
		<location>NMS - Stao A</location>
		<subnetnode>TN NMS (NMS)</subnetnode>
		<cpu>2 CPU</cpu>			
		<memory>8 GB Memory</memory>
		<disk>120 GB Disk (VMDK - Thin Provisioning)</disk>
		<vmh>VMH-NMS-BABS-01 [NMS - Stao A]</vmh>
		<subnet></subnet>
		<dg></dg>
		<mask></mask>				
		<ip></ip>
	</vm>
	<vm>
		<name>APP-NMS-BABS-00</name>
		<description></description>
		<environment>Produktions-Umgebung</environment>
		<location>NMS - Stao A</location>
		<subnetnode>TN NMS (NMS)</subnetnode>
		<cpu>2 CPU</cpu>			
		<memory>8 GB Memory</memory>
		<disk>120 GB Disk (VMDK - Thin Provisioning)</disk>
		<vmh>VMH-NMS-BABS-01 [NMS - Stao A]</vmh>
		<subnet></subnet>
		<dg></dg>
		<mask></mask>				
		<ip></ip>
	</vm>
	<vm>
		<name>PRT-NMS-BABS-00</name>
		<description></description>
		<environment>Produktions-Umgebung</environment>
		<location>NMS - Stao A</location>
		<subnetnode>TN NMS (NMS)</subnetnode>
		<cpu>4 CPU</cpu>			
		<memory>16 GB Memory</memory>
		<disk>500 GB Disk (VMDK - Thin Provisioning)</disk>
		<vmh>VMH-NMS-BABS-01 [NMS - Stao A]</vmh>
		<subnet></subnet>
		<dg></dg>
		<mask></mask>				
		<ip></ip>
	</vm>
	<vm>
		<name>JMP-NMS-BABS-00</name>
		<description></description>
		<environment>Produktions-Umgebung</environment>
		<location>NMS - Stao A</location>
		<subnetnode>TN NMS (NMS)</subnetnode>
		<cpu>2 CPU</cpu>			
		<memory>8 GB Memory</memory>
		<disk>120 GB Disk (VMDK - Thin Provisioning)</disk>
		<vmh>VMH-NMS-BABS-01 [NMS - Stao A]</vmh>
		<subnet></subnet>
		<dg></dg>
		<mask></mask>				
		<ip></ip>
	</vm>
	<vm>
		<name>VCE-NMS-BABS-00</name>
		<description></description>
		<environment>Produktions-Umgebung</environment>
		<location>NMS - Stao A</location>
		<subnetnode>TN NMS (NMS)</subnetnode>
		<cpu>4 CPU</cpu>			
		<memory>16 GB Memory</memory>
		<disk>12 GB Disk (VMDK - Thin Provisioning),1.6 GB Disk (VMDK - Thin Provisioning),25 GB Disk (VMDK - Thin Provisioning),50 GB Disk (VMDK - Thin Provisioning),10 GB Disk (VMDK - Thin Provisioning),10 GB Disk (VMDK - Thin Provisioning),15 GB Disk (VMDK - Thin Provisioning),25 GB Disk (VMDK - Thin Provisioning),1 GB Disk (VMDK - Thin Provisioning),10 GB Disk (VMDK - Thin Provisioning),10 GB Disk (VMDK - Thin Provisioning),100 GB Disk (VMDK - Thin Provisioning),50 GB Disk (VMDK - Thin Provisioning)</disk>
		<vmh>VMH-NMS-BABS-01 [NMS - Stao A]</vmh>
		<subnet></subnet>
		<dg></dg>
		<mask></mask>				
		<ip></ip>
	</vm>
	<vm>
		<name>VBM-NMS-BABS-00</name>
		<description></description>
		<environment>Produktions-Umgebung</environment>
		<location>NMS - Stao A</location>
		<subnetnode>TN NMS (NMS)</subnetnode>
		<cpu>2 CPU</cpu>			
		<memory>12 GB Memory</memory>
		<disk>120 GB Disk (VMDK - Thin Provisioning)</disk>
		<vmh>VMH-NMS-BABS-01 [NMS - Stao A]</vmh>
		<subnet></subnet>
		<dg></dg>
		<mask></mask>				
		<ip></ip>
	</vm>
	<vm>
		<name>MCR-NMS-BABS-00</name>
		<description></description>
		<environment>Produktions-Umgebung</environment>
		<location>NMS - Stao A</location>
		<subnetnode>TN NMS (NMS)</subnetnode>
		<cpu>2 CPU</cpu>			
		<memory>4 GB Memory</memory>
		<disk>120 GB Disk (VMDK - Thin Provisioning)</disk>
		<vmh>VMH-NMS-BABS-01 [NMS - Stao A]</vmh>
		<subnet></subnet>
		<dg></dg>
		<mask></mask>				
		<ip></ip>
	</vm>
	<vm>
		<name>EPO-NMS-BABS-00</name>
		<description></description>
		<environment>Produktions-Umgebung</environment>
		<location>NMS - Stao A</location>
		<subnetnode>TN NMS (NMS)</subnetnode>
		<cpu>4 CPU</cpu>			
		<memory>8 GB Memory</memory>
		<disk>120 GB Disk (VMDK - Thin Provisioning),500 GB Disk (VMDK - Thin Provisioning)</disk>
		<vmh>VMH-NMS-BABS-01 [NMS - Stao A]</vmh>
		<subnet></subnet>
		<dg></dg>
		<mask></mask>				
		<ip></ip>
	</vm>
	<vm>
		<name>CMG-NMS-BABS-00</name>
		<description></description>
		<environment>Produktions-Umgebung</environment>
		<location>NMS - Stao A</location>
		<subnetnode>TN NMS (NMS)</subnetnode>
		<cpu>4 CPU</cpu>			
		<memory>8 GB Memory</memory>
		<disk>120 GB Disk (VMDK - Thin Provisioning),500 GB Disk (VMDK - Thin Provisioning)</disk>
		<vmh>VMH-NMS-BABS-01 [NMS - Stao A]</vmh>
		<subnet></subnet>
		<dg></dg>
		<mask></mask>				
		<ip></ip>
	</vm>
	<vm>
		<name>DFS-NMS-BABS-00</name>
		<description></description>
		<environment>Produktions-Umgebung</environment>
		<location>NMS - Stao A</location>
		<subnetnode>TN NMS (NMS)</subnetnode>
		<cpu>4 CPU</cpu>			
		<memory>4 GB Memory</memory>
		<disk>120 GB Disk (VMDK - Thin Provisioning),500 GB Disk (VMDK - Thin Provisioning)</disk>
		<vmh>VMH-NMS-BABS-01 [NMS - Stao A]</vmh>
		<subnet></subnet>
		<dg></dg>
		<mask></mask>				
		<ip></ip>
	</vm>
	<vm>
		<name>JMP-NMS-BABS-02</name>
		<description></description>
		<environment>Produktions-Umgebung</environment>
		<location>NMS - Stao A</location>
		<subnetnode>TN NMS (NMS)</subnetnode>
		<cpu>2 CPU</cpu>			
		<memory>8 GB Memory</memory>
		<disk>120 GB Disk (VMDK - Thin Provisioning)</disk>
		<vmh>VMH-NMS-BABS-01 [NMS - Stao A]</vmh>
		<subnet></subnet>
		<dg></dg>
		<mask></mask>				
		<ip></ip>
	</vm>
	<vm>
		<name>PRX-NMS-BABS-00</name>
		<description></description>
		<environment>Produktions-Umgebung</environment>
		<location>NMS - Stao A</location>
		<subnetnode>TN NMS (NMS)</subnetnode>
		<cpu>4 CPU</cpu>			
		<memory>8 GB Memory</memory>
		<disk>120 GB Disk (VMDK - Thin Provisioning)</disk>
		<vmh>VMH-NMS-BABS-02 [NMS - Stao A]</vmh>
		<subnet></subnet>
		<dg></dg>
		<mask></mask>				
		<ip></ip>
	</vm>
	<vm>
		<name>VBP-NMS-BABS-01</name>
		<description></description>
		<environment>Produktions-Umgebung</environment>
		<location>NMS - Stao A</location>
		<subnetnode>TN NMS (NMS)</subnetnode>
		<cpu>4 CPU</cpu>			
		<memory>8 GB Memory</memory>
		<disk>120 GB Disk (VMDK - Thin Provisioning)</disk>
		<vmh>VMH-NMS-BABS-02 [NMS - Stao A]</vmh>
		<subnet></subnet>
		<dg></dg>
		<mask></mask>				
		<ip></ip>
	</vm>
	<vm>
		<name>WUS-NMS-BABS-01</name>
		<description></description>
		<environment>Produktions-Umgebung</environment>
		<location>NMS - Stao A</location>
		<subnetnode>TN NMS (NMS)</subnetnode>
		<cpu>4 CPU</cpu>			
		<memory>8 GB Memory</memory>
		<disk>120 GB Disk (VMDK - Thin Provisioning),500 GB Disk (VMDK - Thin Provisioning)</disk>
		<vmh>VMH-NMS-BABS-02 [NMS - Stao A]</vmh>
		<subnet></subnet>
		<dg></dg>
		<mask></mask>				
		<ip></ip>
	</vm>
	<vm>
		<name>RHS-NMS-BABS-00</name>
		<description></description>
		<environment>Produktions-Umgebung</environment>
		<location>NMS - Stao A</location>
		<subnetnode>TN NMS (NMS)</subnetnode>
		<cpu>4 CPU</cpu>			
		<memory>8 GB Memory</memory>
		<disk>120 GB Disk (VMDK - Thin Provisioning),500 GB Disk (VMDK - Thin Provisioning)</disk>
		<vmh>VMH-NMS-BABS-02 [NMS - Stao A]</vmh>
		<subnet></subnet>
		<dg></dg>
		<mask></mask>				
		<ip></ip>
	</vm>
	<vm>
		<name>VCPR-NMS-BABS-10</name>
		<description></description>
		<environment>Produktions-Umgebung</environment>
		<location>NMS - Stao B</location>
		<subnetnode>TN NMS (NMS)</subnetnode>
		<cpu>8 CPU</cpu>			
		<memory>16 GB Memory</memory>
		<disk>300 GB Disk (VMDK - Thin Provisioning),300 GB Disk (VMDK - Thin Provisioning)</disk>
		<vmh>VMH-NMS-BABS-10 [NMS - Stao B]</vmh>
		<subnet></subnet>
		<dg></dg>
		<mask></mask>				
		<ip></ip>
	</vm>
	<vm>
		<name>PRP-NMS-BABS-10</name>
		<description></description>
		<environment>Produktions-Umgebung</environment>
		<location>NMS - Stao B</location>
		<subnetnode>TN NMS (NMS)</subnetnode>
		<cpu>2 CPU</cpu>			
		<memory>8 GB Memory</memory>
		<disk>120 GB Disk (VMDK - Thin Provisioning)</disk>
		<vmh>VMH-NMS-BABS-10 [NMS - Stao B]</vmh>
		<subnet></subnet>
		<dg></dg>
		<mask></mask>				
		<ip></ip>
	</vm>
	<vm>
		<name>VCPM-NMS-BABS-10</name>
		<description></description>
		<environment>Produktions-Umgebung</environment>
		<location>NMS - Stao B</location>
		<subnetnode>TN NMS (NMS)</subnetnode>
		<cpu>8 CPU</cpu>			
		<memory>96 GB Memory</memory>
		<disk>250 GB Disk (VMDK - Thin Provisioning)</disk>
		<vmh>VMH-NMS-BABS-10 [NMS - Stao B]</vmh>
		<subnet></subnet>
		<dg></dg>
		<mask></mask>				
		<ip></ip>
	</vm>
	<vm>
		<name>VCPL-NMS-BABS-10</name>
		<description></description>
		<environment>Produktions-Umgebung</environment>
		<location>NMS - Stao B</location>
		<subnetnode>TN NMS (NMS)</subnetnode>
		<cpu>4 CPU</cpu>			
		<memory>64 GB Memory</memory>
		<disk>1000 GB Disk (VMDK - Thin Provisioning)</disk>
		<vmh>VMH-NMS-BABS-10 [NMS - Stao B]</vmh>
		<subnet></subnet>
		<dg></dg>
		<mask></mask>				
		<ip></ip>
	</vm>
	<vm>
		<name>NPS-NMS-BABS-10</name>
		<description></description>
		<environment>Produktions-Umgebung</environment>
		<location>NMS - Stao B</location>
		<subnetnode>TN NMS (NMS)</subnetnode>
		<cpu>2 CPU</cpu>			
		<memory>8 GB Memory</memory>
		<disk>120 GB Disk (VMDK - Thin Provisioning),20 GB Disk (VMDK - Thin Provisioning)</disk>
		<vmh>VMH-NMS-BABS-10 [NMS - Stao B]</vmh>
		<subnet></subnet>
		<dg></dg>
		<mask></mask>				
		<ip></ip>
	</vm>
	<vm>
		<name>JMP-NMS-BABS-10</name>
		<description></description>
		<environment>Produktions-Umgebung</environment>
		<location>NMS - Stao B</location>
		<subnetnode>TN NMS (NMS)</subnetnode>
		<cpu>4 CPU</cpu>			
		<memory>16 GB Memory</memory>
		<disk>120 GB Disk (VMDK - Thin Provisioning)</disk>
		<vmh>VMH-NMS-BABS-10 [NMS - Stao B]</vmh>
		<subnet></subnet>
		<dg></dg>
		<mask></mask>				
		<ip></ip>
	</vm>
	<vm>
		<name>MCS-NMS-BABS-10</name>
		<description></description>
		<environment>Produktions-Umgebung</environment>
		<location>NMS - Stao B</location>
		<subnetnode>TN NMS (NMS)</subnetnode>
		<cpu>2 CPU</cpu>			
		<memory>8 GB Memory</memory>
		<disk>120 GB Disk (VMDK - Thin Provisioning)</disk>
		<vmh>VMH-NMS-BABS-11 [NMS - Stao B]</vmh>
		<subnet></subnet>
		<dg></dg>
		<mask></mask>				
		<ip></ip>
	</vm>
	<vm>
		<name>APP-NMS-BABS-10</name>
		<description></description>
		<environment>Produktions-Umgebung</environment>
		<location>NMS - Stao B</location>
		<subnetnode>TN NMS (NMS)</subnetnode>
		<cpu>2 CPU</cpu>			
		<memory>8 GB Memory</memory>
		<disk>120 GB Disk (VMDK - Thin Provisioning)</disk>
		<vmh>VMH-NMS-BABS-11 [NMS - Stao B]</vmh>
		<subnet></subnet>
		<dg></dg>
		<mask></mask>				
		<ip></ip>
	</vm>
	<vm>
		<name>PRT-NMS-BABS-10</name>
		<description></description>
		<environment>Produktions-Umgebung</environment>
		<location>NMS - Stao B</location>
		<subnetnode>TN NMS (NMS)</subnetnode>
		<cpu>4 CPU</cpu>			
		<memory>16 GB Memory</memory>
		<disk>500 GB Disk (VMDK - Thin Provisioning)</disk>
		<vmh>VMH-NMS-BABS-11 [NMS - Stao B]</vmh>
		<subnet></subnet>
		<dg></dg>
		<mask></mask>				
		<ip></ip>
	</vm>
	<vm>
		<name>JMP-NMS-BABS-01</name>
		<description></description>
		<environment>Produktions-Umgebung</environment>
		<location>NMS - Stao B</location>
		<subnetnode>TN NMS (NMS)</subnetnode>
		<cpu>2 CPU</cpu>			
		<memory>8 GB Memory</memory>
		<disk>120 GB Disk (VMDK - Thin Provisioning)</disk>
		<vmh>VMH-NMS-BABS-11 [NMS - Stao B]</vmh>
		<subnet></subnet>
		<dg></dg>
		<mask></mask>				
		<ip></ip>
	</vm>
	<vm>
		<name>CMG-NMS-BABS-10</name>
		<description></description>
		<environment>Produktions-Umgebung</environment>
		<location>NMS - Stao B</location>
		<subnetnode>TN NMS (NMS)</subnetnode>
		<cpu>4 CPU</cpu>			
		<memory>8 GB Memory</memory>
		<disk>120 GB Disk (VMDK - Thin Provisioning),500 GB Disk (VMDK - Thin Provisioning)</disk>
		<vmh>VMH-NMS-BABS-11 [NMS - Stao B]</vmh>
		<subnet></subnet>
		<dg></dg>
		<mask></mask>				
		<ip></ip>
	</vm>
	<vm>
		<name>DFS-NMS-BABS-10</name>
		<description></description>
		<environment>Produktions-Umgebung</environment>
		<location>NMS - Stao B</location>
		<subnetnode>TN NMS (NMS)</subnetnode>
		<cpu>4 CPU</cpu>			
		<memory>4 GB Memory</memory>
		<disk>120 GB Disk (VMDK - Thin Provisioning),500 GB Disk (VMDK - Thin Provisioning)</disk>
		<vmh>VMH-NMS-BABS-11 [NMS - Stao B]</vmh>
		<subnet></subnet>
		<dg></dg>
		<mask></mask>				
		<ip></ip>
	</vm>
	<vm>
		<name>JMP-NMS-BABS-12</name>
		<description></description>
		<environment>Produktions-Umgebung</environment>
		<location>NMS - Stao B</location>
		<subnetnode>TN NMS (NMS)</subnetnode>
		<cpu>2 CPU</cpu>			
		<memory>8 GB Memory</memory>
		<disk>120 GB Disk (VMDK - Thin Provisioning)</disk>
		<vmh>VMH-NMS-BABS-11 [NMS - Stao B]</vmh>
		<subnet></subnet>
		<dg></dg>
		<mask></mask>				
		<ip></ip>
	</vm>
	<vm>
		<name>PRX-NMS-BABS-10</name>
		<description></description>
		<environment>Produktions-Umgebung</environment>
		<location>NMS - Stao B</location>
		<subnetnode>TN NMS (NMS)</subnetnode>
		<cpu>4 CPU</cpu>			
		<memory>8 GB Memory</memory>
		<disk>120 GB Disk (VMDK - Thin Provisioning)</disk>
		<vmh>VMH-NMS-BABS-12 [NMS - Stao B]</vmh>
		<subnet></subnet>
		<dg></dg>
		<mask></mask>				
		<ip></ip>
	</vm>
	<vm>
		<name>VBP-NMS-BABS-11</name>
		<description></description>
		<environment>Produktions-Umgebung</environment>
		<location>NMS - Stao B</location>
		<subnetnode>TN NMS (NMS)</subnetnode>
		<cpu>4 CPU</cpu>			
		<memory>8 GB Memory</memory>
		<disk>120 GB Disk (VMDK - Thin Provisioning)</disk>
		<vmh>VMH-NMS-BABS-12 [NMS - Stao B]</vmh>
		<subnet></subnet>
		<dg></dg>
		<mask></mask>				
		<ip></ip>
	</vm>
	<vm>
		<name>WUS-NMS-BABS-11</name>
		<description></description>
		<environment>Produktions-Umgebung</environment>
		<location>NMS - Stao B</location>
		<subnetnode>TN NMS (NMS)</subnetnode>
		<cpu>4 CPU</cpu>			
		<memory>8 GB Memory</memory>
		<disk>120 GB Disk (VMDK - Thin Provisioning),500 GB Disk (VMDK - Thin Provisioning)</disk>
		<vmh>VMH-NMS-BABS-12 [NMS - Stao B]</vmh>
		<subnet></subnet>
		<dg></dg>
		<mask></mask>				
		<ip></ip>
	</vm>
	<vm>
		<name>RHS-NMS-BABS-10</name>
		<description></description>
		<environment>Produktions-Umgebung</environment>
		<location>NMS - Stao B</location>
		<subnetnode>TN NMS (NMS)</subnetnode>
		<cpu>4 CPU</cpu>			
		<memory>8 GB Memory</memory>
		<disk>120 GB Disk (VMDK - Thin Provisioning),500 GB Disk (VMDK - Thin Provisioning)</disk>
		<vmh>VMH-NMS-BABS-12 [NMS - Stao B]</vmh>
		<subnet></subnet>
		<dg></dg>
		<mask></mask>				
		<ip></ip>
	</vm>
	<vm>
		<name>DFS-906-BABS-00</name>
		<description></description>
		<environment>Produktions-Umgebung</environment>
		<location>EAZS</location>
		<subnetnode>TN EAZS (906)</subnetnode>
		<cpu>4 CPU</cpu>			
		<memory>4 GB Memory</memory>
		<disk>120 GB Disk (VMDK - Thin Provisioning),500 GB Disk (VMDK - Thin Provisioning)</disk>
		<vmh>VMH-906-BABS-00 [EAZS]</vmh>
		<subnet></subnet>
		<dg></dg>
		<mask></mask>				
		<ip></ip>
	</vm>
	<vm>
		<name>RDC-906-BABS-00</name>
		<description></description>
		<environment>Produktions-Umgebung</environment>
		<location>EAZS</location>
		<subnetnode>TN EAZS (906)</subnetnode>
		<cpu>4 CPU</cpu>			
		<memory>8 GB Memory</memory>
		<disk>120 GB Disk (VMDK - Thin Provisioning)</disk>
		<vmh>VMH-906-BABS-00 [EAZS]</vmh>
		<subnet></subnet>
		<dg></dg>
		<mask></mask>				
		<ip></ip>
	</vm>
	<vm>
		<name>SPM-906-BABS-00</name>
		<description></description>
		<environment>Produktions-Umgebung</environment>
		<location>EAZS</location>
		<subnetnode>TN EAZS (906)</subnetnode>
		<cpu>4 CPU</cpu>			
		<memory>8 GB Memory</memory>
		<disk>120 GB Disk (VMDK - Thin Provisioning)</disk>
		<vmh>VMH-906-BABS-00 [EAZS]</vmh>
		<subnet></subnet>
		<dg></dg>
		<mask></mask>				
		<ip></ip>
	</vm>
	<vm>
		<name>AM-906-BABS-00</name>
		<description></description>
		<environment>Produktions-Umgebung</environment>
		<location>EAZS</location>
		<subnetnode>TN EAZS (906)</subnetnode>
		<cpu>4 CPU</cpu>			
		<memory>16 GB Memory</memory>
		<disk>120 GB Disk (VMDK - Thin Provisioning)</disk>
		<vmh>VMH-906-BABS-00 [EAZS]</vmh>
		<subnet></subnet>
		<dg></dg>
		<mask></mask>				
		<ip></ip>
	</vm>
	<vm>
		<name>CDF-906-BABS-00</name>
		<description></description>
		<environment>Produktions-Umgebung</environment>
		<location>EAZS</location>
		<subnetnode>TN EAZS (906)</subnetnode>
		<cpu>4 CPU</cpu>			
		<memory>8 GB Memory</memory>
		<disk>120 GB Disk (VMDK - Thin Provisioning)</disk>
		<vmh>VMH-906-BABS-00 [EAZS]</vmh>
		<subnet></subnet>
		<dg></dg>
		<mask></mask>				
		<ip></ip>
	</vm>
	<vm>
		<name>JMP-906-BABS-01</name>
		<description></description>
		<environment>Produktions-Umgebung</environment>
		<location>EAZS</location>
		<subnetnode>TN EAZS (906)</subnetnode>
		<cpu>2 CPU</cpu>			
		<memory>8 GB Memory</memory>
		<disk>120 GB Disk (VMDK - Thin Provisioning)</disk>
		<vmh>VMH-906-BABS-00 [EAZS]</vmh>
		<subnet></subnet>
		<dg></dg>
		<mask></mask>				
		<ip></ip>
	</vm>
	<vm>
		<name>DFS-906-BABS-10</name>
		<description></description>
		<environment>Produktions-Umgebung</environment>
		<location>EAZS</location>
		<subnetnode>TN EAZS (906)</subnetnode>
		<cpu>4 CPU</cpu>			
		<memory>4 GB Memory</memory>
		<disk>120 GB Disk (VMDK - Thin Provisioning),500 GB Disk (VMDK - Thin Provisioning)</disk>
		<vmh>VMH-906-BABS-10 [EAZS]</vmh>
		<subnet></subnet>
		<dg></dg>
		<mask></mask>				
		<ip></ip>
	</vm>
	<vm>
		<name>RDC-906-BABS-10</name>
		<description></description>
		<environment>Produktions-Umgebung</environment>
		<location>EAZS</location>
		<subnetnode>TN EAZS (906)</subnetnode>
		<cpu>4 CPU</cpu>			
		<memory>8 GB Memory</memory>
		<disk>120 GB Disk (VMDK - Thin Provisioning)</disk>
		<vmh>VMH-906-BABS-10 [EAZS]</vmh>
		<subnet></subnet>
		<dg></dg>
		<mask></mask>				
		<ip></ip>
	</vm>
	<vm>
		<name>SPM-906-BABS-10</name>
		<description></description>
		<environment>Produktions-Umgebung</environment>
		<location>EAZS</location>
		<subnetnode>TN EAZS (906)</subnetnode>
		<cpu>4 CPU</cpu>			
		<memory>8 GB Memory</memory>
		<disk>120 GB Disk (VMDK - Thin Provisioning)</disk>
		<vmh>VMH-906-BABS-10 [EAZS]</vmh>
		<subnet></subnet>
		<dg></dg>
		<mask></mask>				
		<ip></ip>
	</vm>
	<vm>
		<name>AM-906-BABS-10</name>
		<description></description>
		<environment>Produktions-Umgebung</environment>
		<location>EAZS</location>
		<subnetnode>TN EAZS (906)</subnetnode>
		<cpu>4 CPU</cpu>			
		<memory>16 GB Memory</memory>
		<disk>120 GB Disk (VMDK - Thin Provisioning)</disk>
		<vmh>VMH-906-BABS-10 [EAZS]</vmh>
		<subnet></subnet>
		<dg></dg>
		<mask></mask>				
		<ip></ip>
	</vm>
	<vm>
		<name>CDF-906-BABS-10</name>
		<description></description>
		<environment>Produktions-Umgebung</environment>
		<location>EAZS</location>
		<subnetnode>TN EAZS (906)</subnetnode>
		<cpu>4 CPU</cpu>			
		<memory>8 GB Memory</memory>
		<disk>120 GB Disk (VMDK - Thin Provisioning)</disk>
		<vmh>VMH-906-BABS-10 [EAZS]</vmh>
		<subnet></subnet>
		<dg></dg>
		<mask></mask>				
		<ip></ip>
	</vm>
	<vm>
		<name>JMP-906-BABS-01</name>
		<description></description>
		<environment>Produktions-Umgebung</environment>
		<location>EAZS</location>
		<subnetnode>TN EAZS (906)</subnetnode>
		<cpu>2 CPU</cpu>			
		<memory>8 GB Memory</memory>
		<disk>120 GB Disk (VMDK - Thin Provisioning)</disk>
		<vmh>VMH-906-BABS-10 [EAZS]</vmh>
		<subnet></subnet>
		<dg></dg>
		<mask></mask>				
		<ip></ip>
	</vm>
	<vm>
		<name>DFS-907-BABS-00</name>
		<description></description>
		<environment>Produktions-Umgebung</environment>
		<location>EAZS</location>
		<subnetnode>TN EAZS (907)</subnetnode>
		<cpu>4 CPU</cpu>			
		<memory>4 GB Memory</memory>
		<disk>120 GB Disk (VMDK - Thin Provisioning),500 GB Disk (VMDK - Thin Provisioning)</disk>
		<vmh>VMH-907-BABS-00 [EAZS]</vmh>
		<subnet></subnet>
		<dg></dg>
		<mask></mask>				
		<ip></ip>
	</vm>
	<vm>
		<name>RDC-907-BABS-00</name>
		<description></description>
		<environment>Produktions-Umgebung</environment>
		<location>EAZS</location>
		<subnetnode>TN EAZS (907)</subnetnode>
		<cpu>4 CPU</cpu>			
		<memory>8 GB Memory</memory>
		<disk>120 GB Disk (VMDK - Thin Provisioning)</disk>
		<vmh>VMH-907-BABS-00 [EAZS]</vmh>
		<subnet></subnet>
		<dg></dg>
		<mask></mask>				
		<ip></ip>
	</vm>
	<vm>
		<name>SPM-907-BABS-00</name>
		<description></description>
		<environment>Produktions-Umgebung</environment>
		<location>EAZS</location>
		<subnetnode>TN EAZS (907)</subnetnode>
		<cpu>4 CPU</cpu>			
		<memory>8 GB Memory</memory>
		<disk>120 GB Disk (VMDK - Thin Provisioning)</disk>
		<vmh>VMH-907-BABS-00 [EAZS]</vmh>
		<subnet></subnet>
		<dg></dg>
		<mask></mask>				
		<ip></ip>
	</vm>
	<vm>
		<name>AM-907-BABS-00</name>
		<description></description>
		<environment>Produktions-Umgebung</environment>
		<location>EAZS</location>
		<subnetnode>TN EAZS (907)</subnetnode>
		<cpu>4 CPU</cpu>			
		<memory>16 GB Memory</memory>
		<disk>120 GB Disk (VMDK - Thin Provisioning)</disk>
		<vmh>VMH-907-BABS-00 [EAZS]</vmh>
		<subnet></subnet>
		<dg></dg>
		<mask></mask>				
		<ip></ip>
	</vm>
	<vm>
		<name>CDF-907-BABS-00</name>
		<description></description>
		<environment>Produktions-Umgebung</environment>
		<location>EAZS</location>
		<subnetnode>TN EAZS (907)</subnetnode>
		<cpu>4 CPU</cpu>			
		<memory>8 GB Memory</memory>
		<disk>120 GB Disk (VMDK - Thin Provisioning)</disk>
		<vmh>VMH-907-BABS-00 [EAZS]</vmh>
		<subnet></subnet>
		<dg></dg>
		<mask></mask>				
		<ip></ip>
	</vm>
	<vm>
		<name>JMP-907-BABS-01</name>
		<description></description>
		<environment>Produktions-Umgebung</environment>
		<location>EAZS</location>
		<subnetnode>TN EAZS (907)</subnetnode>
		<cpu>2 CPU</cpu>			
		<memory>8 GB Memory</memory>
		<disk>120 GB Disk (VMDK - Thin Provisioning)</disk>
		<vmh>VMH-907-BABS-00 [EAZS]</vmh>
		<subnet></subnet>
		<dg></dg>
		<mask></mask>				
		<ip></ip>
	</vm>
	<vm>
		<name>DFS-907-BABS-10</name>
		<description></description>
		<environment>Produktions-Umgebung</environment>
		<location>EAZS</location>
		<subnetnode>TN EAZS (907)</subnetnode>
		<cpu>4 CPU</cpu>			
		<memory>4 GB Memory</memory>
		<disk>120 GB Disk (VMDK - Thin Provisioning),500 GB Disk (VMDK - Thin Provisioning)</disk>
		<vmh>VMH-907-BABS-10 [EAZS]</vmh>
		<subnet></subnet>
		<dg></dg>
		<mask></mask>				
		<ip></ip>
	</vm>
	<vm>
		<name>RDC-907-BABS-10</name>
		<description></description>
		<environment>Produktions-Umgebung</environment>
		<location>EAZS</location>
		<subnetnode>TN EAZS (907)</subnetnode>
		<cpu>4 CPU</cpu>			
		<memory>8 GB Memory</memory>
		<disk>120 GB Disk (VMDK - Thin Provisioning)</disk>
		<vmh>VMH-907-BABS-10 [EAZS]</vmh>
		<subnet></subnet>
		<dg></dg>
		<mask></mask>				
		<ip></ip>
	</vm>
	<vm>
		<name>SPM-907-BABS-10</name>
		<description></description>
		<environment>Produktions-Umgebung</environment>
		<location>EAZS</location>
		<subnetnode>TN EAZS (907)</subnetnode>
		<cpu>4 CPU</cpu>			
		<memory>8 GB Memory</memory>
		<disk>120 GB Disk (VMDK - Thin Provisioning)</disk>
		<vmh>VMH-907-BABS-10 [EAZS]</vmh>
		<subnet></subnet>
		<dg></dg>
		<mask></mask>				
		<ip></ip>
	</vm>
	<vm>
		<name>AM-907-BABS-10</name>
		<description></description>
		<environment>Produktions-Umgebung</environment>
		<location>EAZS</location>
		<subnetnode>TN EAZS (907)</subnetnode>
		<cpu>4 CPU</cpu>			
		<memory>16 GB Memory</memory>
		<disk>120 GB Disk (VMDK - Thin Provisioning)</disk>
		<vmh>VMH-907-BABS-10 [EAZS]</vmh>
		<subnet></subnet>
		<dg></dg>
		<mask></mask>				
		<ip></ip>
	</vm>
	<vm>
		<name>CDF-907-BABS-10</name>
		<description></description>
		<environment>Produktions-Umgebung</environment>
		<location>EAZS</location>
		<subnetnode>TN EAZS (907)</subnetnode>
		<cpu>4 CPU</cpu>			
		<memory>8 GB Memory</memory>
		<disk>120 GB Disk (VMDK - Thin Provisioning)</disk>
		<vmh>VMH-907-BABS-10 [EAZS]</vmh>
		<subnet></subnet>
		<dg></dg>
		<mask></mask>				
		<ip></ip>
	</vm>
	<vm>
		<name>JMP-907-BABS-01</name>
		<description></description>
		<environment>Produktions-Umgebung</environment>
		<location>EAZS</location>
		<subnetnode>TN EAZS (907)</subnetnode>
		<cpu>2 CPU</cpu>			
		<memory>8 GB Memory</memory>
		<disk>120 GB Disk (VMDK - Thin Provisioning)</disk>
		<vmh>VMH-907-BABS-10 [EAZS]</vmh>
		<subnet></subnet>
		<dg></dg>
		<mask></mask>				
		<ip></ip>
	</vm>
	<vm>
		<name>MCS-NMS-BABS-00</name>
		<description></description>
		<environment>Produktions-Umgebung</environment>
		<location>EAZS</location>
		<subnetnode>TN Simulation NMS (NMS)</subnetnode>
		<cpu>2 CPU</cpu>			
		<memory>8 GB Memory</memory>
		<disk>120 GB Disk (VMDK - Thin Provisioning)</disk>
		<vmh>VMH-NMS-BABS-01 [EAZS]</vmh>
		<subnet></subnet>
		<dg></dg>
		<mask></mask>				
		<ip></ip>
	</vm>
	<vm>
		<name>APP-NMS-BABS-00</name>
		<description></description>
		<environment>Produktions-Umgebung</environment>
		<location>EAZS</location>
		<subnetnode>TN Simulation NMS (NMS)</subnetnode>
		<cpu>2 CPU</cpu>			
		<memory>8 GB Memory</memory>
		<disk>120 GB Disk (VMDK - Thin Provisioning)</disk>
		<vmh>VMH-NMS-BABS-01 [EAZS]</vmh>
		<subnet></subnet>
		<dg></dg>
		<mask></mask>				
		<ip></ip>
	</vm>
	<vm>
		<name>PRT-NMS-BABS-00</name>
		<description></description>
		<environment>Produktions-Umgebung</environment>
		<location>EAZS</location>
		<subnetnode>TN Simulation NMS (NMS)</subnetnode>
		<cpu>4 CPU</cpu>			
		<memory>16 GB Memory</memory>
		<disk>500 GB Disk (VMDK - Thin Provisioning)</disk>
		<vmh>VMH-NMS-BABS-01 [EAZS]</vmh>
		<subnet></subnet>
		<dg></dg>
		<mask></mask>				
		<ip></ip>
	</vm>
	<vm>
		<name>JMP-NMS-BABS-00</name>
		<description></description>
		<environment>Produktions-Umgebung</environment>
		<location>EAZS</location>
		<subnetnode>TN Simulation NMS (NMS)</subnetnode>
		<cpu>2 CPU</cpu>			
		<memory>8 GB Memory</memory>
		<disk>120 GB Disk (VMDK - Thin Provisioning)</disk>
		<vmh>VMH-NMS-BABS-01 [EAZS]</vmh>
		<subnet></subnet>
		<dg></dg>
		<mask></mask>				
		<ip></ip>
	</vm>
	<vm>
		<name>VCE-NMS-BABS-00</name>
		<description></description>
		<environment>Produktions-Umgebung</environment>
		<location>EAZS</location>
		<subnetnode>TN Simulation NMS (NMS)</subnetnode>
		<cpu>4 CPU</cpu>			
		<memory>16 GB Memory</memory>
		<disk>12 GB Disk (VMDK - Thin Provisioning),1.6 GB Disk (VMDK - Thin Provisioning),25 GB Disk (VMDK - Thin Provisioning),50 GB Disk (VMDK - Thin Provisioning),10 GB Disk (VMDK - Thin Provisioning),10 GB Disk (VMDK - Thin Provisioning),15 GB Disk (VMDK - Thin Provisioning),25 GB Disk (VMDK - Thin Provisioning),1 GB Disk (VMDK - Thin Provisioning),10 GB Disk (VMDK - Thin Provisioning),10 GB Disk (VMDK - Thin Provisioning),100 GB Disk (VMDK - Thin Provisioning),50 GB Disk (VMDK - Thin Provisioning)</disk>
		<vmh>VMH-NMS-BABS-01 [EAZS]</vmh>
		<subnet></subnet>
		<dg></dg>
		<mask></mask>				
		<ip></ip>
	</vm>
	<vm>
		<name>VBM-NMS-BABS-00</name>
		<description></description>
		<environment>Produktions-Umgebung</environment>
		<location>EAZS</location>
		<subnetnode>TN Simulation NMS (NMS)</subnetnode>
		<cpu>2 CPU</cpu>			
		<memory>12 GB Memory</memory>
		<disk>120 GB Disk (VMDK - Thin Provisioning)</disk>
		<vmh>VMH-NMS-BABS-01 [EAZS]</vmh>
		<subnet></subnet>
		<dg></dg>
		<mask></mask>				
		<ip></ip>
	</vm>
	<vm>
		<name>EPO-NMS-BABS-00</name>
		<description></description>
		<environment>Produktions-Umgebung</environment>
		<location>EAZS</location>
		<subnetnode>TN Simulation NMS (NMS)</subnetnode>
		<cpu>4 CPU</cpu>			
		<memory>8 GB Memory</memory>
		<disk>120 GB Disk (VMDK - Thin Provisioning),500 GB Disk (VMDK - Thin Provisioning)</disk>
		<vmh>VMH-NMS-BABS-01 [EAZS]</vmh>
		<subnet></subnet>
		<dg></dg>
		<mask></mask>				
		<ip></ip>
	</vm>
	<vm>
		<name>CMG-NMS-BABS-00</name>
		<description></description>
		<environment>Produktions-Umgebung</environment>
		<location>EAZS</location>
		<subnetnode>TN Simulation NMS (NMS)</subnetnode>
		<cpu>4 CPU</cpu>			
		<memory>8 GB Memory</memory>
		<disk>120 GB Disk (VMDK - Thin Provisioning),500 GB Disk (VMDK - Thin Provisioning)</disk>
		<vmh>VMH-NMS-BABS-01 [EAZS]</vmh>
		<subnet></subnet>
		<dg></dg>
		<mask></mask>				
		<ip></ip>
	</vm>
	<vm>
		<name>DFS-NMS-BABS-00</name>
		<description></description>
		<environment>Produktions-Umgebung</environment>
		<location>EAZS</location>
		<subnetnode>TN Simulation NMS (NMS)</subnetnode>
		<cpu>4 CPU</cpu>			
		<memory>4 GB Memory</memory>
		<disk>120 GB Disk (VMDK - Thin Provisioning),500 GB Disk (VMDK - Thin Provisioning)</disk>
		<vmh>VMH-NMS-BABS-01 [EAZS]</vmh>
		<subnet></subnet>
		<dg></dg>
		<mask></mask>				
		<ip></ip>
	</vm>
	<vm>
		<name>JMP-NMS-BABS-02</name>
		<description></description>
		<environment>Produktions-Umgebung</environment>
		<location>EAZS</location>
		<subnetnode>TN Simulation NMS (NMS)</subnetnode>
		<cpu>2 CPU</cpu>			
		<memory>8 GB Memory</memory>
		<disk>120 GB Disk (VMDK - Thin Provisioning)</disk>
		<vmh>VMH-NMS-BABS-01 [EAZS]</vmh>
		<subnet></subnet>
		<dg></dg>
		<mask></mask>				
		<ip></ip>
	</vm>
	<vm>
		<name>PRX-NMS-BABS-00</name>
		<description></description>
		<environment>Produktions-Umgebung</environment>
		<location>EAZS</location>
		<subnetnode>TN Simulation NMS (NMS)</subnetnode>
		<cpu>4 CPU</cpu>			
		<memory>8 GB Memory</memory>
		<disk>120 GB Disk (VMDK - Thin Provisioning)</disk>
		<vmh>VMH-NMS-BABS-02 [EAZS]</vmh>
		<subnet></subnet>
		<dg></dg>
		<mask></mask>				
		<ip></ip>
	</vm>
	<vm>
		<name>VBP-NMS-BABS-01</name>
		<description></description>
		<environment>Produktions-Umgebung</environment>
		<location>EAZS</location>
		<subnetnode>TN Simulation NMS (NMS)</subnetnode>
		<cpu>4 CPU</cpu>			
		<memory>8 GB Memory</memory>
		<disk>120 GB Disk (VMDK - Thin Provisioning)</disk>
		<vmh>VMH-NMS-BABS-02 [EAZS]</vmh>
		<subnet></subnet>
		<dg></dg>
		<mask></mask>				
		<ip></ip>
	</vm>
	<vm>
		<name>WUS-NMS-BABS-01</name>
		<description></description>
		<environment>Produktions-Umgebung</environment>
		<location>EAZS</location>
		<subnetnode>TN Simulation NMS (NMS)</subnetnode>
		<cpu>4 CPU</cpu>			
		<memory>8 GB Memory</memory>
		<disk>120 GB Disk (VMDK - Thin Provisioning),500 GB Disk (VMDK - Thin Provisioning)</disk>
		<vmh>VMH-NMS-BABS-02 [EAZS]</vmh>
		<subnet></subnet>
		<dg></dg>
		<mask></mask>				
		<ip></ip>
	</vm>
	<vm>
		<name>RHS-NMS-BABS-00</name>
		<description></description>
		<environment>Produktions-Umgebung</environment>
		<location>EAZS</location>
		<subnetnode>TN Simulation NMS (NMS)</subnetnode>
		<cpu>4 CPU</cpu>			
		<memory>8 GB Memory</memory>
		<disk>120 GB Disk (VMDK - Thin Provisioning),500 GB Disk (VMDK - Thin Provisioning)</disk>
		<vmh>VMH-NMS-BABS-02 [EAZS]</vmh>
		<subnet></subnet>
		<dg></dg>
		<mask></mask>				
		<ip></ip>
	</vm>
	<vm>
		<name>MCS-NMS-BABS-10</name>
		<description></description>
		<environment>Produktions-Umgebung</environment>
		<location>EAZS</location>
		<subnetnode>TN Simulation NMS (NMS)</subnetnode>
		<cpu>2 CPU</cpu>			
		<memory>8 GB Memory</memory>
		<disk>120 GB Disk (VMDK - Thin Provisioning)</disk>
		<vmh>VMH-NMS-BABS-11 [EAZS]</vmh>
		<subnet></subnet>
		<dg></dg>
		<mask></mask>				
		<ip></ip>
	</vm>
	<vm>
		<name>APP-NMS-BABS-10</name>
		<description></description>
		<environment>Produktions-Umgebung</environment>
		<location>EAZS</location>
		<subnetnode>TN Simulation NMS (NMS)</subnetnode>
		<cpu>2 CPU</cpu>			
		<memory>8 GB Memory</memory>
		<disk>120 GB Disk (VMDK - Thin Provisioning)</disk>
		<vmh>VMH-NMS-BABS-11 [EAZS]</vmh>
		<subnet></subnet>
		<dg></dg>
		<mask></mask>				
		<ip></ip>
	</vm>
	<vm>
		<name>PRT-NMS-BABS-10</name>
		<description></description>
		<environment>Produktions-Umgebung</environment>
		<location>EAZS</location>
		<subnetnode>TN Simulation NMS (NMS)</subnetnode>
		<cpu>4 CPU</cpu>			
		<memory>16 GB Memory</memory>
		<disk>500 GB Disk (VMDK - Thin Provisioning)</disk>
		<vmh>VMH-NMS-BABS-11 [EAZS]</vmh>
		<subnet></subnet>
		<dg></dg>
		<mask></mask>				
		<ip></ip>
	</vm>
	<vm>
		<name>JMP-NMS-BABS-10</name>
		<description></description>
		<environment>Produktions-Umgebung</environment>
		<location>EAZS</location>
		<subnetnode>TN Simulation NMS (NMS)</subnetnode>
		<cpu>2 CPU</cpu>			
		<memory>8 GB Memory</memory>
		<disk>120 GB Disk (VMDK - Thin Provisioning)</disk>
		<vmh>VMH-NMS-BABS-11 [EAZS]</vmh>
		<subnet></subnet>
		<dg></dg>
		<mask></mask>				
		<ip></ip>
	</vm>
	<vm>
		<name>CMG-NMS-BABS-10</name>
		<description></description>
		<environment>Produktions-Umgebung</environment>
		<location>EAZS</location>
		<subnetnode>TN Simulation NMS (NMS)</subnetnode>
		<cpu>4 CPU</cpu>			
		<memory>8 GB Memory</memory>
		<disk>120 GB Disk (VMDK - Thin Provisioning),500 GB Disk (VMDK - Thin Provisioning)</disk>
		<vmh>VMH-NMS-BABS-11 [EAZS]</vmh>
		<subnet></subnet>
		<dg></dg>
		<mask></mask>				
		<ip></ip>
	</vm>
	<vm>
		<name>DFS-NMS-BABS-10</name>
		<description></description>
		<environment>Produktions-Umgebung</environment>
		<location>EAZS</location>
		<subnetnode>TN Simulation NMS (NMS)</subnetnode>
		<cpu>4 CPU</cpu>			
		<memory>4 GB Memory</memory>
		<disk>120 GB Disk (VMDK - Thin Provisioning),500 GB Disk (VMDK - Thin Provisioning)</disk>
		<vmh>VMH-NMS-BABS-11 [EAZS]</vmh>
		<subnet></subnet>
		<dg></dg>
		<mask></mask>				
		<ip></ip>
	</vm>
	<vm>
		<name>JMP-NMS-BABS-12</name>
		<description></description>
		<environment>Produktions-Umgebung</environment>
		<location>EAZS</location>
		<subnetnode>TN Simulation NMS (NMS)</subnetnode>
		<cpu>2 CPU</cpu>			
		<memory>8 GB Memory</memory>
		<disk>120 GB Disk (VMDK - Thin Provisioning)</disk>
		<vmh>VMH-NMS-BABS-11 [EAZS]</vmh>
		<subnet></subnet>
		<dg></dg>
		<mask></mask>				
		<ip></ip>
	</vm>
	<vm>
		<name>PRX-NMS-BABS-10</name>
		<description></description>
		<environment>Produktions-Umgebung</environment>
		<location>EAZS</location>
		<subnetnode>TN Simulation NMS (NMS)</subnetnode>
		<cpu>4 CPU</cpu>			
		<memory>8 GB Memory</memory>
		<disk>120 GB Disk (VMDK - Thin Provisioning)</disk>
		<vmh>VMH-NMS-BABS-12 [EAZS]</vmh>
		<subnet></subnet>
		<dg></dg>
		<mask></mask>				
		<ip></ip>
	</vm>
	<vm>
		<name>VBP-NMS-BABS-10</name>
		<description></description>
		<environment>Produktions-Umgebung</environment>
		<location>EAZS</location>
		<subnetnode>TN Simulation NMS (NMS)</subnetnode>
		<cpu>4 CPU</cpu>			
		<memory>8 GB Memory</memory>
		<disk>120 GB Disk (VMDK - Thin Provisioning)</disk>
		<vmh>VMH-NMS-BABS-12 [EAZS]</vmh>
		<subnet></subnet>
		<dg></dg>
		<mask></mask>				
		<ip></ip>
	</vm>
	<vm>
		<name>WUS-NMS-BABS-10</name>
		<description></description>
		<environment>Produktions-Umgebung</environment>
		<location>EAZS</location>
		<subnetnode>TN Simulation NMS (NMS)</subnetnode>
		<cpu>4 CPU</cpu>			
		<memory>8 GB Memory</memory>
		<disk>120 GB Disk (VMDK - Thin Provisioning),500 GB Disk (VMDK - Thin Provisioning)</disk>
		<vmh>VMH-NMS-BABS-12 [EAZS]</vmh>
		<subnet></subnet>
		<dg></dg>
		<mask></mask>				
		<ip></ip>
	</vm>
	<vm>
		<name>RHS-NMS-BABS-10</name>
		<description></description>
		<environment>Produktions-Umgebung</environment>
		<location>EAZS</location>
		<subnetnode>TN Simulation NMS (NMS)</subnetnode>
		<cpu>4 CPU</cpu>			
		<memory>8 GB Memory</memory>
		<disk>120 GB Disk (VMDK - Thin Provisioning),500 GB Disk (VMDK - Thin Provisioning)</disk>
		<vmh>VMH-NMS-BABS-12 [EAZS]</vmh>
		<subnet></subnet>
		<dg></dg>
		<mask></mask>				
		<ip></ip>
	</vm>
	<vm>
		<name>DFS-50X-BABS-00</name>
		<description></description>
		<environment>Produktions-Umgebung</environment>
		<location></location>
		<subnetnode>TN FUB (50X)</subnetnode>
		<cpu>4 CPU</cpu>			
		<memory>4 GB Memory</memory>
		<disk>120 GB Disk (VMDK - Thin Provisioning),500 GB Disk (VMDK - Thin Provisioning)</disk>
		<vmh>432d594a-3c01-11e9-ae90-e393b4df5e9e</vmh>
		<subnet></subnet>
		<dg></dg>
		<mask></mask>				
		<ip></ip>
	</vm>
	<vm>
		<name>RDC-50X-BABS-00</name>
		<description></description>
		<environment>Produktions-Umgebung</environment>
		<location></location>
		<subnetnode>TN FUB (50X)</subnetnode>
		<cpu>4 CPU</cpu>			
		<memory>8 GB Memory</memory>
		<disk>120 GB Disk (VMDK - Thin Provisioning)</disk>
		<vmh>432d594a-3c01-11e9-ae90-e393b4df5e9e</vmh>
		<subnet></subnet>
		<dg></dg>
		<mask></mask>				
		<ip></ip>
	</vm>
	<vm>
		<name>SPM-50X-BABS-00</name>
		<description></description>
		<environment>Produktions-Umgebung</environment>
		<location></location>
		<subnetnode>TN FUB (50X)</subnetnode>
		<cpu>4 CPU</cpu>			
		<memory>8 GB Memory</memory>
		<disk>120 GB Disk (VMDK - Thin Provisioning)</disk>
		<vmh>432d594a-3c01-11e9-ae90-e393b4df5e9e</vmh>
		<subnet></subnet>
		<dg></dg>
		<mask></mask>				
		<ip></ip>
	</vm>
	<vm>
		<name>AM-50X-BABS-00</name>
		<description></description>
		<environment>Produktions-Umgebung</environment>
		<location></location>
		<subnetnode>TN FUB (50X)</subnetnode>
		<cpu>4 CPU</cpu>			
		<memory>16 GB Memory</memory>
		<disk>120 GB Disk (VMDK - Thin Provisioning)</disk>
		<vmh>432d594a-3c01-11e9-ae90-e393b4df5e9e</vmh>
		<subnet></subnet>
		<dg></dg>
		<mask></mask>				
		<ip></ip>
	</vm>
	<vm>
		<name>CDF-50X-BABS-00</name>
		<description></description>
		<environment>Produktions-Umgebung</environment>
		<location></location>
		<subnetnode>TN FUB (50X)</subnetnode>
		<cpu>4 CPU</cpu>			
		<memory>8 GB Memory</memory>
		<disk>120 GB Disk (VMDK - Thin Provisioning)</disk>
		<vmh>432d594a-3c01-11e9-ae90-e393b4df5e9e</vmh>
		<subnet></subnet>
		<dg></dg>
		<mask></mask>				
		<ip></ip>
	</vm>
	<vm>
		<name>JMP-50X-BABS-01</name>
		<description></description>
		<environment>Produktions-Umgebung</environment>
		<location></location>
		<subnetnode>TN FUB (50X)</subnetnode>
		<cpu>2 CPU</cpu>			
		<memory>8 GB Memory</memory>
		<disk>120 GB Disk (VMDK - Thin Provisioning)</disk>
		<vmh>432d594a-3c01-11e9-ae90-e393b4df5e9e</vmh>
		<subnet></subnet>
		<dg></dg>
		<mask></mask>				
		<ip></ip>
	</vm>
	<vm>
		<name>MCS-NMS-BABS-00</name>
		<description></description>
		<environment>Test-Umgebung</environment>
		<location>Vevey</location>
		<subnetnode>TN NMS (NMS)</subnetnode>
		<cpu>2 CPU</cpu>			
		<memory>8 GB Memory</memory>
		<disk>120 GB Disk (VMDK - Thin Provisioning)</disk>
		<vmh>VMH-NMS-BABS-01 [Vevey]</vmh>
		<subnet></subnet>
		<dg></dg>
		<mask></mask>				
		<ip></ip>
	</vm>
	<vm>
		<name>APP-NMS-BABS-00</name>
		<description></description>
		<environment>Test-Umgebung</environment>
		<location>Vevey</location>
		<subnetnode>TN NMS (NMS)</subnetnode>
		<cpu>2 CPU</cpu>			
		<memory>8 GB Memory</memory>
		<disk>120 GB Disk (VMDK - Thin Provisioning)</disk>
		<vmh>VMH-NMS-BABS-01 [Vevey]</vmh>
		<subnet></subnet>
		<dg></dg>
		<mask></mask>				
		<ip></ip>
	</vm>
	<vm>
		<name>PRT-NMS-BABS-00</name>
		<description></description>
		<environment>Test-Umgebung</environment>
		<location>Vevey</location>
		<subnetnode>TN NMS (NMS)</subnetnode>
		<cpu>4 CPU</cpu>			
		<memory>16 GB Memory</memory>
		<disk>500 GB Disk (VMDK - Thin Provisioning)</disk>
		<vmh>VMH-NMS-BABS-01 [Vevey]</vmh>
		<subnet></subnet>
		<dg></dg>
		<mask></mask>				
		<ip></ip>
	</vm>
	<vm>
		<name>JMP-NMS-BABS-00</name>
		<description></description>
		<environment>Test-Umgebung</environment>
		<location>Vevey</location>
		<subnetnode>TN NMS (NMS)</subnetnode>
		<cpu>2 CPU</cpu>			
		<memory>8 GB Memory</memory>
		<disk>120 GB Disk (VMDK - Thin Provisioning)</disk>
		<vmh>VMH-NMS-BABS-01 [Vevey]</vmh>
		<subnet></subnet>
		<dg></dg>
		<mask></mask>				
		<ip></ip>
	</vm>
	<vm>
		<name>VCE-NMS-BABS-00</name>
		<description></description>
		<environment>Test-Umgebung</environment>
		<location>Vevey</location>
		<subnetnode>TN NMS (NMS)</subnetnode>
		<cpu>4 CPU</cpu>			
		<memory>16 GB Memory</memory>
		<disk>12 GB Disk (VMDK - Thin Provisioning),1.6 GB Disk (VMDK - Thin Provisioning),25 GB Disk (VMDK - Thin Provisioning),50 GB Disk (VMDK - Thin Provisioning),10 GB Disk (VMDK - Thin Provisioning),10 GB Disk (VMDK - Thin Provisioning),15 GB Disk (VMDK - Thin Provisioning),25 GB Disk (VMDK - Thin Provisioning),1 GB Disk (VMDK - Thin Provisioning),10 GB Disk (VMDK - Thin Provisioning),10 GB Disk (VMDK - Thin Provisioning),100 GB Disk (VMDK - Thin Provisioning),50 GB Disk (VMDK - Thin Provisioning)</disk>
		<vmh>VMH-NMS-BABS-01 [Vevey]</vmh>
		<subnet></subnet>
		<dg></dg>
		<mask></mask>				
		<ip></ip>
	</vm>
	<vm>
		<name>VBM-NMS-BABS-00</name>
		<description></description>
		<environment>Test-Umgebung</environment>
		<location>Vevey</location>
		<subnetnode>TN NMS (NMS)</subnetnode>
		<cpu>2 CPU</cpu>			
		<memory>12 GB Memory</memory>
		<disk>120 GB Disk (VMDK - Thin Provisioning)</disk>
		<vmh>VMH-NMS-BABS-01 [Vevey]</vmh>
		<subnet></subnet>
		<dg></dg>
		<mask></mask>				
		<ip></ip>
	</vm>
	<vm>
		<name>MCR-NMS-BABS-00</name>
		<description></description>
		<environment>Test-Umgebung</environment>
		<location>Vevey</location>
		<subnetnode>TN NMS (NMS)</subnetnode>
		<cpu>2 CPU</cpu>			
		<memory>4 GB Memory</memory>
		<disk>120 GB Disk (VMDK - Thin Provisioning)</disk>
		<vmh>VMH-NMS-BABS-01 [Vevey]</vmh>
		<subnet></subnet>
		<dg></dg>
		<mask></mask>				
		<ip></ip>
	</vm>
	<vm>
		<name>EPO-NMS-BABS-00</name>
		<description></description>
		<environment>Test-Umgebung</environment>
		<location>Vevey</location>
		<subnetnode>TN NMS (NMS)</subnetnode>
		<cpu>4 CPU</cpu>			
		<memory>8 GB Memory</memory>
		<disk>120 GB Disk (VMDK - Thin Provisioning),500 GB Disk (VMDK - Thin Provisioning)</disk>
		<vmh>VMH-NMS-BABS-01 [Vevey]</vmh>
		<subnet></subnet>
		<dg></dg>
		<mask></mask>				
		<ip></ip>
	</vm>
	<vm>
		<name>CMG-NMS-BABS-00</name>
		<description></description>
		<environment>Test-Umgebung</environment>
		<location>Vevey</location>
		<subnetnode>TN NMS (NMS)</subnetnode>
		<cpu>4 CPU</cpu>			
		<memory>8 GB Memory</memory>
		<disk>120 GB Disk (VMDK - Thin Provisioning),500 GB Disk (VMDK - Thin Provisioning)</disk>
		<vmh>VMH-NMS-BABS-01 [Vevey]</vmh>
		<subnet></subnet>
		<dg></dg>
		<mask></mask>				
		<ip></ip>
	</vm>
	<vm>
		<name>DFS-NMS-BABS-00</name>
		<description></description>
		<environment>Test-Umgebung</environment>
		<location>Vevey</location>
		<subnetnode>TN NMS (NMS)</subnetnode>
		<cpu>4 CPU</cpu>			
		<memory>4 GB Memory</memory>
		<disk>120 GB Disk (VMDK - Thin Provisioning),500 GB Disk (VMDK - Thin Provisioning)</disk>
		<vmh>VMH-NMS-BABS-01 [Vevey]</vmh>
		<subnet></subnet>
		<dg></dg>
		<mask></mask>				
		<ip></ip>
	</vm>
	<vm>
		<name>VCPR-NMS-BABS-00</name>
		<description></description>
		<environment>Test-Umgebung</environment>
		<location>Vevey</location>
		<subnetnode>TN NMS (NMS)</subnetnode>
		<cpu>8 CPU</cpu>			
		<memory>16 GB Memory</memory>
		<disk>300 GB Disk (VMDK - Thin Provisioning),300 GB Disk (VMDK - Thin Provisioning)</disk>
		<vmh>VMH-NMS-BABS-01 [Vevey]</vmh>
		<subnet></subnet>
		<dg></dg>
		<mask></mask>				
		<ip></ip>
	</vm>
	<vm>
		<name>PRP-NMS-BABS-00</name>
		<description></description>
		<environment>Test-Umgebung</environment>
		<location>Vevey</location>
		<subnetnode>TN NMS (NMS)</subnetnode>
		<cpu>2 CPU</cpu>			
		<memory>8 GB Memory</memory>
		<disk>120 GB Disk (VMDK - Thin Provisioning)</disk>
		<vmh>VMH-NMS-BABS-01 [Vevey]</vmh>
		<subnet></subnet>
		<dg></dg>
		<mask></mask>				
		<ip></ip>
	</vm>
	<vm>
		<name>VCPM-NMS-BABS-00</name>
		<description></description>
		<environment>Test-Umgebung</environment>
		<location>Vevey</location>
		<subnetnode>TN NMS (NMS)</subnetnode>
		<cpu>8 CPU</cpu>			
		<memory>96 GB Memory</memory>
		<disk>250 GB Disk (VMDK - Thin Provisioning)</disk>
		<vmh>VMH-NMS-BABS-01 [Vevey]</vmh>
		<subnet></subnet>
		<dg></dg>
		<mask></mask>				
		<ip></ip>
	</vm>
	<vm>
		<name>VCPL-NMS-BABS-00</name>
		<description></description>
		<environment>Test-Umgebung</environment>
		<location>Vevey</location>
		<subnetnode>TN NMS (NMS)</subnetnode>
		<cpu>4 CPU</cpu>			
		<memory>64 GB Memory</memory>
		<disk>1000 GB Disk (VMDK - Thin Provisioning)</disk>
		<vmh>VMH-NMS-BABS-01 [Vevey]</vmh>
		<subnet></subnet>
		<dg></dg>
		<mask></mask>				
		<ip></ip>
	</vm>
	<vm>
		<name>NPS-NMS-BABS-00</name>
		<description></description>
		<environment>Test-Umgebung</environment>
		<location>Vevey</location>
		<subnetnode>TN NMS (NMS)</subnetnode>
		<cpu>4 CPU</cpu>			
		<memory>8 GB Memory</memory>
		<disk>120 GB Disk (VMDK - Thin Provisioning),20 GB Disk (VMDK - Thin Provisioning)</disk>
		<vmh>VMH-NMS-BABS-01 [Vevey]</vmh>
		<subnet></subnet>
		<dg></dg>
		<mask></mask>				
		<ip></ip>
	</vm>
	<vm>
		<name>JMP-NMS-BABS-01</name>
		<description></description>
		<environment>Test-Umgebung</environment>
		<location>Vevey</location>
		<subnetnode>TN NMS (NMS)</subnetnode>
		<cpu>4 CPU</cpu>			
		<memory>16 GB Memory</memory>
		<disk>120 GB Disk (VMDK - Thin Provisioning)</disk>
		<vmh>VMH-NMS-BABS-01 [Vevey]</vmh>
		<subnet></subnet>
		<dg></dg>
		<mask></mask>				
		<ip></ip>
	</vm>
	<vm>
		<name>JMP-NMS-BABS-02</name>
		<description></description>
		<environment>Test-Umgebung</environment>
		<location>Vevey</location>
		<subnetnode>TN NMS (NMS)</subnetnode>
		<cpu>2 CPU</cpu>			
		<memory>8 GB Memory</memory>
		<disk>120 GB Disk (VMDK - Thin Provisioning)</disk>
		<vmh>VMH-NMS-BABS-01 [Vevey]</vmh>
		<subnet></subnet>
		<dg></dg>
		<mask></mask>				
		<ip></ip>
	</vm>
	<vm>
		<name>MDC-NMS-BABS-00</name>
		<description></description>
		<environment>Test-Umgebung</environment>
		<location>Vevey</location>
		<subnetnode>TN NMS (NMS)</subnetnode>
		<cpu>2 CPU</cpu>			
		<memory>8 GB Memory</memory>
		<disk>120 GB Disk (VMDK - Thin Provisioning)</disk>
		<vmh>VMH-NMS-BABS-01 [Vevey]</vmh>
		<subnet>10.90.25.0/29 - VLAN-2000 subzone-nms-services-infra-services</subnet>
		<dg></dg>
		<mask>255.255.255.248</mask>				
		<ip>10.90.25.4</ip>
	</vm>
	<vm>
		<name>WUS-NMS-BABS-00</name>
		<description></description>
		<environment>Test-Umgebung</environment>
		<location>Vevey</location>
		<subnetnode>TN NMS (NMS)</subnetnode>
		<cpu>4 CPU</cpu>			
		<memory>8 GB Memory</memory>
		<disk>60 GB Disk (VMDK - Thin Provisioning),500 GB Disk (VMDK - Thin Provisioning)</disk>
		<vmh>VMH-NMS-BABS-01 [Vevey]</vmh>
		<subnet></subnet>
		<dg></dg>
		<mask></mask>				
		<ip></ip>
	</vm>
	<vm>
		<name>RHS-NMS-BABS-00</name>
		<description></description>
		<environment>Test-Umgebung</environment>
		<location>Vevey</location>
		<subnetnode>TN NMS (NMS)</subnetnode>
		<cpu>4 CPU</cpu>			
		<memory>8 GB Memory</memory>
		<disk>120 GB Disk (VMDK - Thin Provisioning),500 GB Disk (VMDK - Thin Provisioning)</disk>
		<vmh>VMH-NMS-BABS-01 [Vevey]</vmh>
		<subnet></subnet>
		<dg></dg>
		<mask></mask>				
		<ip></ip>
	</vm>
	<vm>
		<name>PRX-NMS-BABS-00</name>
		<description></description>
		<environment>Test-Umgebung</environment>
		<location>Vevey</location>
		<subnetnode>TN NMS (NMS)</subnetnode>
		<cpu>4 CPU</cpu>			
		<memory>8 GB Memory</memory>
		<disk>120 GB Disk (VMDK - Thin Provisioning)</disk>
		<vmh>VMH-NMS-BABS-02 [Vevey]</vmh>
		<subnet></subnet>
		<dg></dg>
		<mask></mask>				
		<ip></ip>
	</vm>
	<vm>
		<name>MCS-NMS-BABS-10</name>
		<description></description>
		<environment>Test-Umgebung</environment>
		<location>Vevey</location>
		<subnetnode>TN NMS (NMS)</subnetnode>
		<cpu>2 CPU</cpu>			
		<memory>8 GB Memory</memory>
		<disk>120 GB Disk (VMDK - Thin Provisioning)</disk>
		<vmh>VMH-NMS-BABS-11 [Vevey]</vmh>
		<subnet></subnet>
		<dg></dg>
		<mask></mask>				
		<ip></ip>
	</vm>
	<vm>
		<name>APP-NMS-BABS-10</name>
		<description></description>
		<environment>Test-Umgebung</environment>
		<location>Vevey</location>
		<subnetnode>TN NMS (NMS)</subnetnode>
		<cpu>2 CPU</cpu>			
		<memory>8 GB Memory</memory>
		<disk>120 GB Disk (VMDK - Thin Provisioning)</disk>
		<vmh>VMH-NMS-BABS-11 [Vevey]</vmh>
		<subnet></subnet>
		<dg></dg>
		<mask></mask>				
		<ip></ip>
	</vm>
	<vm>
		<name>PRT-NMS-BABS-10</name>
		<description></description>
		<environment>Test-Umgebung</environment>
		<location>Vevey</location>
		<subnetnode>TN NMS (NMS)</subnetnode>
		<cpu>4 CPU</cpu>			
		<memory>16 GB Memory</memory>
		<disk>500 GB Disk (VMDK - Thin Provisioning)</disk>
		<vmh>VMH-NMS-BABS-11 [Vevey]</vmh>
		<subnet></subnet>
		<dg></dg>
		<mask></mask>				
		<ip></ip>
	</vm>
	<vm>
		<name>JMP-NMS-BABS-01</name>
		<description></description>
		<environment>Test-Umgebung</environment>
		<location>Vevey</location>
		<subnetnode>TN NMS (NMS)</subnetnode>
		<cpu>2 CPU</cpu>			
		<memory>8 GB Memory</memory>
		<disk>120 GB Disk (VMDK - Thin Provisioning)</disk>
		<vmh>VMH-NMS-BABS-11 [Vevey]</vmh>
		<subnet></subnet>
		<dg></dg>
		<mask></mask>				
		<ip></ip>
	</vm>
	<vm>
		<name>CMG-NMS-BABS-10</name>
		<description></description>
		<environment>Test-Umgebung</environment>
		<location>Vevey</location>
		<subnetnode>TN NMS (NMS)</subnetnode>
		<cpu>4 CPU</cpu>			
		<memory>8 GB Memory</memory>
		<disk>120 GB Disk (VMDK - Thin Provisioning),500 GB Disk (VMDK - Thin Provisioning)</disk>
		<vmh>VMH-NMS-BABS-11 [Vevey]</vmh>
		<subnet></subnet>
		<dg></dg>
		<mask></mask>				
		<ip></ip>
	</vm>
	<vm>
		<name>DFS-NMS-BABS-10</name>
		<description></description>
		<environment>Test-Umgebung</environment>
		<location>Vevey</location>
		<subnetnode>TN NMS (NMS)</subnetnode>
		<cpu>4 CPU</cpu>			
		<memory>4 GB Memory</memory>
		<disk>120 GB Disk (VMDK - Thin Provisioning),500 GB Disk (VMDK - Thin Provisioning)</disk>
		<vmh>VMH-NMS-BABS-11 [Vevey]</vmh>
		<subnet></subnet>
		<dg></dg>
		<mask></mask>				
		<ip></ip>
	</vm>
	<vm>
		<name>VCPR-NMS-BABS-10</name>
		<description></description>
		<environment>Test-Umgebung</environment>
		<location>Vevey</location>
		<subnetnode>TN NMS (NMS)</subnetnode>
		<cpu>8 CPU</cpu>			
		<memory>16 GB Memory</memory>
		<disk>300 GB Disk (VMDK - Thin Provisioning),300 GB Disk (VMDK - Thin Provisioning)</disk>
		<vmh>VMH-NMS-BABS-11 [Vevey]</vmh>
		<subnet></subnet>
		<dg></dg>
		<mask></mask>				
		<ip></ip>
	</vm>
	<vm>
		<name>PRP-NMS-BABS-10</name>
		<description></description>
		<environment>Test-Umgebung</environment>
		<location>Vevey</location>
		<subnetnode>TN NMS (NMS)</subnetnode>
		<cpu>2 CPU</cpu>			
		<memory>8 GB Memory</memory>
		<disk>120 GB Disk (VMDK - Thin Provisioning)</disk>
		<vmh>VMH-NMS-BABS-11 [Vevey]</vmh>
		<subnet></subnet>
		<dg></dg>
		<mask></mask>				
		<ip></ip>
	</vm>
	<vm>
		<name>VCPM-NMS-BABS-10</name>
		<description></description>
		<environment>Test-Umgebung</environment>
		<location>Vevey</location>
		<subnetnode>TN NMS (NMS)</subnetnode>
		<cpu>8 CPU</cpu>			
		<memory>96 GB Memory</memory>
		<disk>250 GB Disk (VMDK - Thin Provisioning)</disk>
		<vmh>VMH-NMS-BABS-11 [Vevey]</vmh>
		<subnet></subnet>
		<dg></dg>
		<mask></mask>				
		<ip></ip>
	</vm>
	<vm>
		<name>VCPL-NMS-BABS-10</name>
		<description></description>
		<environment>Test-Umgebung</environment>
		<location>Vevey</location>
		<subnetnode>TN NMS (NMS)</subnetnode>
		<cpu>4 CPU</cpu>			
		<memory>64 GB Memory</memory>
		<disk>1000 GB Disk (VMDK - Thin Provisioning)</disk>
		<vmh>VMH-NMS-BABS-11 [Vevey]</vmh>
		<subnet></subnet>
		<dg></dg>
		<mask></mask>				
		<ip></ip>
	</vm>
	<vm>
		<name>NPS-NMS-BABS-10</name>
		<description></description>
		<environment>Test-Umgebung</environment>
		<location>Vevey</location>
		<subnetnode>TN NMS (NMS)</subnetnode>
		<cpu>2 CPU</cpu>			
		<memory>8 GB Memory</memory>
		<disk>120 GB Disk (VMDK - Thin Provisioning),20 GB Disk (VMDK - Thin Provisioning)</disk>
		<vmh>VMH-NMS-BABS-11 [Vevey]</vmh>
		<subnet></subnet>
		<dg></dg>
		<mask></mask>				
		<ip></ip>
	</vm>
	<vm>
		<name>JMP-NMS-BABS-10</name>
		<description></description>
		<environment>Test-Umgebung</environment>
		<location>Vevey</location>
		<subnetnode>TN NMS (NMS)</subnetnode>
		<cpu>4 CPU</cpu>			
		<memory>16 GB Memory</memory>
		<disk>120 GB Disk (VMDK - Thin Provisioning)</disk>
		<vmh>VMH-NMS-BABS-11 [Vevey]</vmh>
		<subnet></subnet>
		<dg></dg>
		<mask></mask>				
		<ip></ip>
	</vm>
	<vm>
		<name>JMP-NMS-BABS-12</name>
		<description></description>
		<environment>Test-Umgebung</environment>
		<location>Vevey</location>
		<subnetnode>TN NMS (NMS)</subnetnode>
		<cpu>2 CPU</cpu>			
		<memory>8 GB Memory</memory>
		<disk>120 GB Disk (VMDK - Thin Provisioning)</disk>
		<vmh>VMH-NMS-BABS-11 [Vevey]</vmh>
		<subnet></subnet>
		<dg></dg>
		<mask></mask>				
		<ip></ip>
	</vm>
	<vm>
		<name>MDC-NMS-BABS-10</name>
		<description></description>
		<environment>Test-Umgebung</environment>
		<location>Vevey</location>
		<subnetnode>TN NMS (NMS)</subnetnode>
		<cpu>2 CPU</cpu>			
		<memory>8 GB Memory</memory>
		<disk>120 GB Disk (VMDK - Thin Provisioning)</disk>
		<vmh>VMH-NMS-BABS-11 [Vevey]</vmh>
		<subnet>10.90.25.0/29 - VLAN-2000 subzone-nms-services-infra-services</subnet>
		<dg></dg>
		<mask>255.255.255.248</mask>				
		<ip>10.90.25.5</ip>
	</vm>
	<vm>
		<name>DFS-984-POOL-00</name>
		<description></description>
		<environment>Test-Umgebung</environment>
		<location>Vevey</location>
		<subnetnode>TN RA1 (984)</subnetnode>
		<cpu>4 CPU</cpu>			
		<memory>4 GB Memory</memory>
		<disk>120 GB Disk (VMDK - Thin Provisioning),500 GB Disk (VMDK - Thin Provisioning)</disk>
		<vmh>VMH-984-POOL-00 [Vevey]</vmh>
		<subnet>10.124.1.0/29 - VLAN-2000 subzone-ch-services-infra-services</subnet>
		<dg></dg>
		<mask>255.255.255.248</mask>				
		<ip>10.124.1.1</ip>
	</vm>
	<vm>
		<name>RDC-984-POOL-00</name>
		<description></description>
		<environment>Test-Umgebung</environment>
		<location>Vevey</location>
		<subnetnode>TN RA1 (984)</subnetnode>
		<cpu>4 CPU</cpu>			
		<memory>8 GB Memory</memory>
		<disk>120 GB Disk (VMDK - Thin Provisioning)</disk>
		<vmh>VMH-984-POOL-00 [Vevey]</vmh>
		<subnet></subnet>
		<dg></dg>
		<mask></mask>				
		<ip></ip>
	</vm>
	<vm>
		<name>SPM-984-POOL-00</name>
		<description></description>
		<environment>Test-Umgebung</environment>
		<location>Vevey</location>
		<subnetnode>TN RA1 (984)</subnetnode>
		<cpu>4 CPU</cpu>			
		<memory>8 GB Memory</memory>
		<disk>120 GB Disk (VMDK - Thin Provisioning)</disk>
		<vmh>VMH-984-POOL-00 [Vevey]</vmh>
		<subnet></subnet>
		<dg></dg>
		<mask></mask>				
		<ip></ip>
	</vm>
	<vm>
		<name>AM-984-POOL-00</name>
		<description></description>
		<environment>Test-Umgebung</environment>
		<location>Vevey</location>
		<subnetnode>TN RA1 (984)</subnetnode>
		<cpu>4 CPU</cpu>			
		<memory>16 GB Memory</memory>
		<disk>120 GB Disk (VMDK - Thin Provisioning)</disk>
		<vmh>VMH-984-POOL-00 [Vevey]</vmh>
		<subnet></subnet>
		<dg></dg>
		<mask></mask>				
		<ip></ip>
	</vm>
	<vm>
		<name>CDF-984-POOL-00</name>
		<description></description>
		<environment>Test-Umgebung</environment>
		<location>Vevey</location>
		<subnetnode>TN RA1 (984)</subnetnode>
		<cpu>4 CPU</cpu>			
		<memory>8 GB Memory</memory>
		<disk>120 GB Disk (VMDK - Thin Provisioning)</disk>
		<vmh>VMH-984-POOL-00 [Vevey]</vmh>
		<subnet></subnet>
		<dg></dg>
		<mask></mask>				
		<ip></ip>
	</vm>
	<vm>
		<name>JMP-984-POOL-00</name>
		<description></description>
		<environment>Test-Umgebung</environment>
		<location>Vevey</location>
		<subnetnode>TN RA1 (984)</subnetnode>
		<cpu>2 CPU</cpu>			
		<memory>8 GB Memory</memory>
		<disk>120 GB Disk (VMDK - Thin Provisioning)</disk>
		<vmh>VMH-984-POOL-00 [Vevey]</vmh>
		<subnet></subnet>
		<dg></dg>
		<mask></mask>				
		<ip></ip>
	</vm>
	<vm>
		<name>DFS-984-POOL-10</name>
		<description></description>
		<environment>Test-Umgebung</environment>
		<location>Vevey</location>
		<subnetnode>TN RA1 (984)</subnetnode>
		<cpu>4 CPU</cpu>			
		<memory>4 GB Memory</memory>
		<disk>120 GB Disk (VMDK - Thin Provisioning),500 GB Disk (VMDK - Thin Provisioning)</disk>
		<vmh>VMH-984-POOL-10 [Vevey]</vmh>
		<subnet></subnet>
		<dg></dg>
		<mask></mask>				
		<ip></ip>
	</vm>
	<vm>
		<name>RDC-984-POOL-10</name>
		<description></description>
		<environment>Test-Umgebung</environment>
		<location>Vevey</location>
		<subnetnode>TN RA1 (984)</subnetnode>
		<cpu>4 CPU</cpu>			
		<memory>8 GB Memory</memory>
		<disk>120 GB Disk (VMDK - Thin Provisioning)</disk>
		<vmh>VMH-984-POOL-10 [Vevey]</vmh>
		<subnet></subnet>
		<dg></dg>
		<mask></mask>				
		<ip></ip>
	</vm>
	<vm>
		<name>SPM-984-POOL-10</name>
		<description></description>
		<environment>Test-Umgebung</environment>
		<location>Vevey</location>
		<subnetnode>TN RA1 (984)</subnetnode>
		<cpu>4 CPU</cpu>			
		<memory>8 GB Memory</memory>
		<disk>120 GB Disk (VMDK - Thin Provisioning)</disk>
		<vmh>VMH-984-POOL-10 [Vevey]</vmh>
		<subnet></subnet>
		<dg></dg>
		<mask></mask>				
		<ip></ip>
	</vm>
	<vm>
		<name>AM-984-POOL-10</name>
		<description></description>
		<environment>Test-Umgebung</environment>
		<location>Vevey</location>
		<subnetnode>TN RA1 (984)</subnetnode>
		<cpu>4 CPU</cpu>			
		<memory>16 GB Memory</memory>
		<disk>120 GB Disk (VMDK - Thin Provisioning)</disk>
		<vmh>VMH-984-POOL-10 [Vevey]</vmh>
		<subnet></subnet>
		<dg></dg>
		<mask></mask>				
		<ip></ip>
	</vm>
	<vm>
		<name>CDF-984-POOL-10</name>
		<description></description>
		<environment>Test-Umgebung</environment>
		<location>Vevey</location>
		<subnetnode>TN RA1 (984)</subnetnode>
		<cpu>4 CPU</cpu>			
		<memory>8 GB Memory</memory>
		<disk>120 GB Disk (VMDK - Thin Provisioning)</disk>
		<vmh>VMH-984-POOL-10 [Vevey]</vmh>
		<subnet></subnet>
		<dg></dg>
		<mask></mask>				
		<ip></ip>
	</vm>
	<vm>
		<name>JMP-984-POOL-01</name>
		<description></description>
		<environment>Test-Umgebung</environment>
		<location>Vevey</location>
		<subnetnode>TN RA1 (984)</subnetnode>
		<cpu>2 CPU</cpu>			
		<memory>8 GB Memory</memory>
		<disk>120 GB Disk (VMDK - Thin Provisioning)</disk>
		<vmh>VMH-984-POOL-10 [Vevey]</vmh>
		<subnet></subnet>
		<dg></dg>
		<mask></mask>				
		<ip></ip>
	</vm>
	<vm>
		<name>DFS-986-POOL-00</name>
		<description></description>
		<environment>Test-Umgebung</environment>
		<location>Vevey</location>
		<subnetnode>TN RA2 (986)</subnetnode>
		<cpu>4 CPU</cpu>			
		<memory>4 GB Memory</memory>
		<disk>120 GB Disk (VMDK - Thin Provisioning),500 GB Disk (VMDK - Thin Provisioning)</disk>
		<vmh>VMH-986-POOL-00 [Vevey]</vmh>
		<subnet></subnet>
		<dg></dg>
		<mask></mask>				
		<ip></ip>
	</vm>
	<vm>
		<name>RDC-986-POOL-00</name>
		<description></description>
		<environment>Test-Umgebung</environment>
		<location>Vevey</location>
		<subnetnode>TN RA2 (986)</subnetnode>
		<cpu>4 CPU</cpu>			
		<memory>8 GB Memory</memory>
		<disk>120 GB Disk (VMDK - Thin Provisioning)</disk>
		<vmh>VMH-986-POOL-00 [Vevey]</vmh>
		<subnet></subnet>
		<dg></dg>
		<mask></mask>				
		<ip></ip>
	</vm>
	<vm>
		<name>SPM-986-POOL-00</name>
		<description></description>
		<environment>Test-Umgebung</environment>
		<location>Vevey</location>
		<subnetnode>TN RA2 (986)</subnetnode>
		<cpu>4 CPU</cpu>			
		<memory>8 GB Memory</memory>
		<disk>120 GB Disk (VMDK - Thin Provisioning)</disk>
		<vmh>VMH-986-POOL-00 [Vevey]</vmh>
		<subnet></subnet>
		<dg></dg>
		<mask></mask>				
		<ip></ip>
	</vm>
	<vm>
		<name>AM-986-POOL-00</name>
		<description></description>
		<environment>Test-Umgebung</environment>
		<location>Vevey</location>
		<subnetnode>TN RA2 (986)</subnetnode>
		<cpu>4 CPU</cpu>			
		<memory>16 GB Memory</memory>
		<disk>120 GB Disk (VMDK - Thin Provisioning)</disk>
		<vmh>VMH-986-POOL-00 [Vevey]</vmh>
		<subnet></subnet>
		<dg></dg>
		<mask></mask>				
		<ip></ip>
	</vm>
	<vm>
		<name>CDF-986-POOL-00</name>
		<description></description>
		<environment>Test-Umgebung</environment>
		<location>Vevey</location>
		<subnetnode>TN RA2 (986)</subnetnode>
		<cpu>4 CPU</cpu>			
		<memory>8 GB Memory</memory>
		<disk>120 GB Disk (VMDK - Thin Provisioning)</disk>
		<vmh>VMH-986-POOL-00 [Vevey]</vmh>
		<subnet></subnet>
		<dg></dg>
		<mask></mask>				
		<ip></ip>
	</vm>
	<vm>
		<name>JMP-986-POOL-01</name>
		<description></description>
		<environment>Test-Umgebung</environment>
		<location>Vevey</location>
		<subnetnode>TN RA2 (986)</subnetnode>
		<cpu>2 CPU</cpu>			
		<memory>8 GB Memory</memory>
		<disk>120 GB Disk (VMDK - Thin Provisioning)</disk>
		<vmh>VMH-986-POOL-00 [Vevey]</vmh>
		<subnet></subnet>
		<dg></dg>
		<mask></mask>				
		<ip></ip>
	</vm>
	<vm>
		<name>DFS-981-POOL-00</name>
		<description></description>
		<environment>Test-Umgebung</environment>
		<location>Vevey</location>
		<subnetnode>TN IA1 (981)</subnetnode>
		<cpu>4 CPU</cpu>			
		<memory>4 GB Memory</memory>
		<disk>120 GB Disk (VMDK - Thin Provisioning),500 GB Disk (VMDK - Thin Provisioning)</disk>
		<vmh>VMH-981-POOL-00 [Vevey]</vmh>
		<subnet></subnet>
		<dg></dg>
		<mask></mask>				
		<ip></ip>
	</vm>
	<vm>
		<name>RDC-981-POOL-00</name>
		<description></description>
		<environment>Test-Umgebung</environment>
		<location>Vevey</location>
		<subnetnode>TN IA1 (981)</subnetnode>
		<cpu>4 CPU</cpu>			
		<memory>8 GB Memory</memory>
		<disk>120 GB Disk (VMDK - Thin Provisioning)</disk>
		<vmh>VMH-981-POOL-00 [Vevey]</vmh>
		<subnet></subnet>
		<dg></dg>
		<mask></mask>				
		<ip></ip>
	</vm>
	<vm>
		<name>SPM-981-POOL-00</name>
		<description></description>
		<environment>Test-Umgebung</environment>
		<location>Vevey</location>
		<subnetnode>TN IA1 (981)</subnetnode>
		<cpu>4 CPU</cpu>			
		<memory>8 GB Memory</memory>
		<disk>120 GB Disk (VMDK - Thin Provisioning)</disk>
		<vmh>VMH-981-POOL-00 [Vevey]</vmh>
		<subnet></subnet>
		<dg></dg>
		<mask></mask>				
		<ip></ip>
	</vm>
	<vm>
		<name>AM-981-POOL-00</name>
		<description></description>
		<environment>Test-Umgebung</environment>
		<location>Vevey</location>
		<subnetnode>TN IA1 (981)</subnetnode>
		<cpu>4 CPU</cpu>			
		<memory>16 GB Memory</memory>
		<disk>120 GB Disk (VMDK - Thin Provisioning)</disk>
		<vmh>VMH-981-POOL-00 [Vevey]</vmh>
		<subnet></subnet>
		<dg></dg>
		<mask></mask>				
		<ip></ip>
	</vm>
	<vm>
		<name>CDF-981-POOL-00</name>
		<description></description>
		<environment>Test-Umgebung</environment>
		<location>Vevey</location>
		<subnetnode>TN IA1 (981)</subnetnode>
		<cpu>4 CPU</cpu>			
		<memory>8 GB Memory</memory>
		<disk>120 GB Disk (VMDK - Thin Provisioning)</disk>
		<vmh>VMH-981-POOL-00 [Vevey]</vmh>
		<subnet></subnet>
		<dg></dg>
		<mask></mask>				
		<ip></ip>
	</vm>
	<vm>
		<name>JMP-981-POOL-01</name>
		<description></description>
		<environment>Test-Umgebung</environment>
		<location>Vevey</location>
		<subnetnode>TN IA1 (981)</subnetnode>
		<cpu>2 CPU</cpu>			
		<memory>8 GB Memory</memory>
		<disk>120 GB Disk (VMDK - Thin Provisioning)</disk>
		<vmh>VMH-981-POOL-00 [Vevey]</vmh>
		<subnet></subnet>
		<dg></dg>
		<mask></mask>				
		<ip></ip>
	</vm>
	<vm>
		<name>VBP-981-POOL-00</name>
		<description></description>
		<environment>Test-Umgebung</environment>
		<location>Vevey</location>
		<subnetnode>TN IA1 (981)</subnetnode>
		<cpu>2 CPU</cpu>			
		<memory>8 GB Memory</memory>
		<disk>120 GB Disk (VMDK - Thin Provisioning)</disk>
		<vmh>VMH-981-POOL-00 [Vevey]</vmh>
		<subnet></subnet>
		<dg></dg>
		<mask></mask>				
		<ip></ip>
	</vm>
</vms>
<!-- Actifsource ID=[44ad8516-35ac-11e9-9d58-25409887bb2a,d020f1af-d10d-11e8-91a3-55b260d274ec,bd0f0925-ef19-11e8-be8a-b748ff8f0a75,Hash] -->
