<?xml version="1.0" encoding="utf-8"?>
<db:book version="5" xmlns:xlink="http://www.w3.org/1999/xlink" xmlns:db="http://docbook.org/ns/docbook">
	<db:title>ReferenceDocumentWithäöü</db:title>
	
	<db:para>Lorem ipsum dolor sit amet, consetetur sadipscing elitr, sed diam 
	         nonumy eirmod tempor invidunt ut labore et dolore magna aliquyam erat, 
	         sed diam voluptua. At vero eos et accusam et justo duo dolores et ea rebum. 
	         Stet clita kasd gubergren, no sea takimata sanctus est Lorem ipsum dolor sit amet.</db:para>
	<db:para>dsfadfasdfasdfasdf</db:para>
	<db:para>dsfadfasdfasdfasdf</db:para>
	<db:para>dsfadfasdfasdfasdf</db:para>
	<db:para>dsfadfasdfasdfasdf</db:para>
	<db:para>dsfadfasdfasdfasdf</db:para>
	<db:para>dsfadfasdfasdfasdf</db:para>
	<db:para>dsfadfasdfasdfasdf</db:para>
	<db:chapter>
		<db:title>SubDocumentB</db:title>
		<db:para></db:para>
		
		
		<db:section>
			<db:title>SubDocumentB_2</db:title>
			<db:para></db:para>
			
			
			
		</db:section>
		<db:section>
			<db:title>SubDocumentB_1</db:title>
			<db:para></db:para>
			
			
			
		</db:section>
	</db:chapter>
	<db:chapter>
		<db:title>SubDocumentA</db:title>
		<db:para></db:para>
		
		
		
	</db:chapter>
	<db:chapter>
		<db:title>Level 1</db:title>
		<db:para>Lorem ipsum dolor sit amet, consetetur sadipscing elitr, sed diam 
		         nonumy eirmod tempor invidunt ut labore et dolore magna aliquyam erat, 
		         sed diam voluptua. At vero eos et accusam et justo duo dolores et ea rebum. 
		         Stet clita kasd gubergren, no sea takimata sanctus est Lorem ipsum dolor sit amet.</db:para>
		<db:para>Teste</db:para>
		
		<db:section>
			<db:title>Level 2</db:title>
			<db:para>Lorem ipsum dolor sit amet, consetetur sadipscing elitr, sed diam 
			         nonumy eirmod tempor invidunt ut labore et dolore magna aliquyam erat, 
			         sed diam voluptua. At vero eos et accusam et justo duo dolores et ea rebum. 
			         Stet clita kasd gubergren, no sea takimata sanctus est Lorem ipsum dolor sit amet.</db:para>
			<db:para>Lorem ipsum dolor sit amet, consetetur sadipscing elitr, sed diam 
			         nonumy eirmod tempor invidunt ut labore et dolore magna aliquyam erat, 
			         sed diam voluptua. At vero eos et accusam et justo duo dolores et ea rebum. 
			         Stet clita kasd gubergren, no sea takimata sanctus est Lorem ipsum dolor sit amet.</db:para>
			
			<db:section>
				<db:title>Level 3</db:title>
				<db:para></db:para>
				<db:para>Lorem ipsum dolor sit amet, consetetur sadipscing elitr, sed diam 
				         nonumy eirmod tempor invidunt ut labore et dolore magna aliquyam erat, 
				         sed diam voluptua. At vero eos et accusam et justo duo dolores et ea rebum. 
				         Stet clita kasd gubergren, no sea takimata sanctus est Lorem ipsum dolor sit amet.</db:para>
				
				<db:section>
					<db:title>Level 4</db:title>
					<db:para></db:para>
					<db:para>Lorem ipsum dolor sit amet, consetetur sadipscing elitr, sed diam 
					         nonumy eirmod tempor invidunt ut labore et dolore magna aliquyam erat, 
					         sed diam voluptua. At vero eos et accusam et justo duo dolores et ea rebum. 
					         Stet clita kasd gubergren, no sea takimata sanctus est Lorem ipsum dolor sit amet.</db:para>
					
					<db:section>
						<db:title>Level 5</db:title>
						<db:para></db:para>
						<db:para>Lorem ipsum dolor sit amet, consetetur sadipscing elitr, sed diam 
						         nonumy eirmod tempor invidunt ut labore et dolore magna aliquyam erat, 
						         sed diam voluptua. At vero eos et accusam et justo duo dolores et ea rebum. 
						         Stet clita kasd gubergren, no sea takimata sanctus est Lorem ipsum dolor sit amet.</db:para>
						<db:note>
							<db:para>This is an open block styled as NOTE.</db:para>
							<db:para>This is an open block</db:para>
							<db:orderedlist numeration="lowerroman">
								<db:listitem>
									<db:para>item 1</db:para>
								</db:listitem>
								<db:listitem>
									<db:para>item 2</db:para>
								</db:listitem>
								<db:listitem>
									<db:para>item 3</db:para>
								</db:listitem>
							</db:orderedlist>
						</db:note>
						<db:tip>
							This is a tip.
						</db:tip>
						<db:important>
							This is important.
						</db:important>
						<db:warning>
							This is a warning.
						</db:warning>
						<db:caution>
							This is caution.
						</db:caution>
						<db:para>A regular listing block without highlighting:</db:para>
						<db:programmlisting>
							class Main {
							   void main(String ars[]) {
							       int a = 1;
							   }
							}
						</db:programmlisting>
						<db:programmlisting>
							class Main {
							   void main(String ars[]) {
							       int a = 1;
							   }
							}
							class Main {
							   void main(String ars[]) { &lt;1&gt;
							       int a = 1;
							   }
							}
							class Main {
							   void main(String ars[]) { &lt;1&gt;
							       int a = 1;
							   }
							}
							class Main {
							   void main(String ars[]) { &lt;1&gt;
							       int a = 1;
							   }
							}
						</db:programmlisting>
						
						
					</db:section>
				</db:section>
			</db:section>
		</db:section>
	</db:chapter>
</db:book>
<!-- Actifsource ID=[17b682a2-3de9-11e6-9bf8-29c5fda07fa3,c78ac92e-4669-11e5-ba74-cb2e95044e1c,Hash] -->
